MANIFEST.in
README.rst
setup.py
bddocs.egg-info/PKG-INFO
bddocs.egg-info/SOURCES.txt
bddocs.egg-info/dependency_links.txt
bddocs.egg-info/requires.txt
bddocs.egg-info/top_level.txt
bddocs.egg-info/zip-safe
bddocs/config/__init__.py
bddocs/config/i18n.py
bddocs/config/settings.py
bddocs/model/__init__.py
bddocs/model/artifact.py
bddocs/model/documentation.py
bddocs/model/feature.py
bddocs/model/scenario.py
bddocs/model/step.py
bddocs/src/graphs/__init__.py
bddocs/src/graphs/graphs.py
bddocs/src/html/__init__.py
bddocs/src/html/html.py
bddocs/src/markup/__init__.py
bddocs/src/markup/markup.py
bddocs/src/pdf/__init__.py
bddocs/src/pdf/pdf.py
bddocs/src/pdf/style.py