Metadata-Version: 1.0
Name: bddocs
Version: 0.44
Summary: Create end-user readable docs in Pythonic way
Home-page: http://github.com/yurireeis/bddocs
Author: Yuri Reis & Alexandre Reis
Author-email: UNKNOWN
License: UNKNOWN
Platform: All
